[
   {
      "ip": "127.0.0.1",
      "port": 8080,
      "user": "myuser",
      "pass": "MySecretPassword",
      "config": "/home/myuser/ft_userdata/user_data/config.json"
   },
   {
      "ip": "127.0.0.1",      
      "port": 8081,
      "user": "myuser",
      "pass": "MySecretPassword",
      "config": "/home/myuser/ft_userdata/user_data/config.json"
   },
   {
      "ip": "127.0.0.1",      
      "port": 8082,
      "user": "myuser",
      "pass": "MySecretPassword",
      "config": "/home/myuser/ft_userdata/user_data/config.json"
   }
]
